[
    {
        "name": "arctic-viewer",
        "path": "tonic-applications",
        "submodule": true
    },{
        "name": "arctic-viewer-ios",
        "path": "tonic-applications",
        "submodule": true
    },{
        "name": "tonic-widgets",
        "path": "tonic-components",
        "submodule": true
    },{
        "name": "tonic-mouse-handler",
        "path": "tonic-components",
        "submodule": true
    },{
        "name": "tonic-data-manager",
        "path": "tonic-components",
        "submodule": true
    },{
        "name": "tonic-image-builder",
        "path": "tonic-components",
        "submodule": true
    },{
        "name": "tonic-query-data-model",
        "path": "tonic-components",
        "submodule": true
    },{
        "name": "tonic-data-generator",
        "path": "tonic-tools",
        "submodule": false
    },{
        "name": "tonic-site-generator",
        "path": "tonic-tools",
        "submodule": true
    },{
        "name": "tonic-vtk",
        "path": "tonic-components",
        "submodule": false
    }
]
